{
    "name": "SPO.05.5032.1382.38.1",
    "description": "NO as Tamsweg Untere Postgasse",
    "unitOfMeasurement": {
        "name": "ug.m-3",
        "symbol": "ug.m-3",
        "definition": "http://dd.eionet.europa.eu/vocabulary/uom/concentration/ug.m-3"
    },
    "observedArea": {
        "type": "Point",
        "coordinates": [
            13.808333333,
            47.125833333
        ]
    },
    "phenomenonTime": "2017-12-31T23:00:00Z/2018-01-01T01:00:00Z",
    "properties": {
        "temporalExtent": "2017-12-31T23:00:00Z/2018-01-01T01:00:00Z",
        "commenttemporalExtent": "Redundant due to phenomenonTime in DS",
        "baseTime": "2017-12-31T23:00:00Z",
        "spacing": "PT1H",
        "status": "Some Code",
        "sampledMedium": "http://inspire.ec.europa.eu/codelist/MediaValue/air",
        "intendedObservationSpacing": "PT1H",
        "numberTimeSteps": 2,
        "parameter": [{
                "name": "some name",
                "value": "some value"
            }],
    		"cumulative": "FALSE",
    		"accumulationIntervalLength": "PT1H",
    		"accumulationAnchorTime": "T00:00:00",
    		"startAnchorPoint": "T00:00:00",
    		"endAnchorPoint": "T00:00:00",
    		"maxGapPeriod": "PT8H"
    },
    "ObservedProperty": {
        "name": "NO",
        "definition": "http://dd.eionet.europa.eu/vocabulary/aq/pollutant/38",
    },
    "Sensor": {
        "name": "API200EU",
        "description": "http://dd.eionet.europa.eu/vocabulary/aq/measurementequipment/API200EU",
    },
    "Observations": [{
            "phenomenonTime": "2017-12-31T23:00:00Z/2018-01-01T00:00:00Z",
            "result": 12.5962142944,
            "FeatureOfInterest": {
                "name": "SAM.05.5032.1382.38.1",
                "description": "Air quality sample SAM.05.5032.1382.38.1",
                "feature": {
                    "type": "Point",
                    "coordinates": [
                        13.808333333333334,
                        47.12583333333333
                    ]
                },
                "properties": {
          					"comment": "some comment",
          					"quality": "Bad",
          					"nilReason": "Not measured",
          					"relatedObservation": "http://...",
          					"qualifier": "further data quality info",
          					"processing": "raw",
          					"source": "Info as MD_DataIdentification",
          					"censoredReason": "uncensored",
          					"uncertainty": "uncertainty information",
          					"interpolationType": "http://.../linear",
          					"aggregationDuration": "T00:00:00"
                }
            }
        }, {
            "phenomenonTime": "2018-01-01T00:00:00Z/2018-01-01T01:00:00Z",
            "result": 7.7946872711,
            "FeatureOfInterest": {
                "name": "SAM.05.5032.1382.38.1",
                "description": "Air quality sample SAM.05.5032.1382.38.1",
                "feature": {
                    "type": "Point",
                    "coordinates": [
                        13.808333333333334,
                        47.12583333333333
                    ]
                },
                "properties": {
            					"comment": "some comment",
            					"quality": "Good",
            					"nilReason": "NA",
            					"relatedObservation": "http://...",
            					"qualifier": "further data quality info",
            					"processing": "raw",
            					"source": "Info as MD_DataIdentification",
            					"censoredReason": "uncensored",
            					"uncertainty": "uncertainty information",
            					"interpolationType": "http://.../linear",
            					"aggregationDuration": "T00:00:00"
                }
            }
        }
    ]
}
